{
  "id": "ELBA-2025-17412",
  "vendor": "Oracle",
  "type": "Bug Fix Advisory (ELBA)",
  "kernel_type": "RHCK",
  "title": "e2fsprogs bug fix and enhancement update",
  "issuedDate": "2025-10-07T00:00:00Z",
  "updatedDate": "2025-10-07T00:00:00Z",
  "pubDate": "2025-10-07T00:00:00Z",
  "dateStr": "2025-10-07",
  "url": "https://linux.oracle.com/errata/ELBA-2025-17412.html",
  "severity": "None",
  "overview": "An update for Oracle Linux is now available for Oracle Linux 8.",
  "description": "* Mon Sep 01 2025 Pavel Reichl <preichl@redhat.com>\n- libext2fs: fix unix_io's Direct I/O support\n- Related: RHEL-106939",
  "affected_products": [
    "Oracle Linux 8 for x86_64",
    "Oracle Linux 8 for aarch64"
  ],
  "cves": [],
  "packages": [
    "e2fsprogs-libs-1.45.6-7.el8_10.x86_64",
    "libcom_err-1.45.6-7.el8_10.i686",
    "libss-1.45.6-7.el8_10.i686",
    "libcom_err-devel-1.45.6-7.el8_10.x86_64",
    "libcom_err-1.45.6-7.el8_10.x86_64",
    "e2fsprogs-1.45.6-7.el8_10.src",
    "e2fsprogs-static-1.45.6-7.el8_10.x86_64",
    "e2fsprogs-libs-1.45.6-7.el8_10.i686",
    "e2fsprogs-devel-1.45.6-7.el8_10.i686",
    "e2fsprogs-1.45.6-7.el8_10.x86_64",
    "e2fsprogs-static-1.45.6-7.el8_10.i686",
    "libcom_err-devel-1.45.6-7.el8_10.i686",
    "e2fsprogs-devel-1.45.6-7.el8_10.x86_64",
    "libss-1.45.6-7.el8_10.x86_64"
  ],
  "full_text": "* Mon Sep 01 2025 Pavel Reichl <preichl@redhat.com>\n- libext2fs: fix unix_io's Direct I/O support\n- Related: RHEL-106939\n\nReferences:\nhttps://linux.oracle.com/errata/ELBA-2025-17412.html"
}