{
  "id": "ELBA-2025-28052",
  "vendor": "Oracle",
  "type": "Bug Fix Advisory (ELBA)",
  "kernel_type": "AppStream",
  "title": " rust-sequoia-sq  bug fix update",
  "issuedDate": "2025-12-15T00:00:00Z",
  "updatedDate": "2025-12-15T00:00:00Z",
  "pubDate": "2025-12-15T00:00:00Z",
  "dateStr": "2025-12-15",
  "url": "https://linux.oracle.com/errata/ELBA-2025-28052.html",
  "severity": "None",
  "overview": "An update for Oracle Linux is now available for Oracle Linux 10.",
  "description": "[1.3.1.1-1.0.2]\n- Put 'Requires' openssl-libs in correct placeholder [Orabug: 38742109]\n\n[1.3.1.1-1.0.1]\n- Hard require needed openssl-libs [Orabug: 38742109]",
  "affected_products": [
    "Oracle Linux 10 for x86_64",
    "Oracle Linux 10 for aarch64"
  ],
  "cves": [],
  "packages": [
    "sequoia-sq-1.3.1.1-1.0.2.el10.x86_64",
    "rust-sequoia-sq-1.3.1.1-1.0.2.el10.src"
  ],
  "full_text": "[1.3.1.1-1.0.2]\n- Put 'Requires' openssl-libs in correct placeholder [Orabug: 38742109]\n\n[1.3.1.1-1.0.1]\n- Hard require needed openssl-libs [Orabug: 38742109]\n\nReferences:\nhttps://linux.oracle.com/errata/ELBA-2025-28052.html"
}