{
  "id": "ELBA-2025-15892",
  "vendor": "Oracle",
  "type": "Bug Fix Advisory (ELBA)",
  "kernel_type": "AppStream",
  "title": "xorg-x11-drv-wacom bug fix and enhancement update",
  "issuedDate": "2025-09-16T00:00:00Z",
  "updatedDate": "2025-09-16T00:00:00Z",
  "pubDate": "2025-09-16T00:00:00Z",
  "dateStr": "2025-09-16",
  "url": "https://linux.oracle.com/errata/ELBA-2025-15892.html",
  "severity": "None",
  "overview": "An update for Oracle Linux is now available for Oracle Linux 9.",
  "description": "[1.0.0-4]\n- Fix axis inversion on the first relative dial  (RHEL-106467)\n\n[1.0.0-3]\n- Map ABS_THROTTLE to ring2 on all dualring devices (RHEL-106467)\n\n[1.0.0-2]\n- Add support for Wacom Intuos Pro 3rd Gen (RHEL-106467)",
  "affected_products": [
    "Oracle Linux 9 for x86_64",
    "Oracle Linux 9 for aarch64"
  ],
  "cves": [],
  "packages": [
    "xorg-x11-drv-wacom-1.0.0-4.el9_6.src",
    "xorg-x11-drv-wacom-serial-support-1.0.0-4.el9_6.x86_64",
    "xorg-x11-drv-wacom-1.0.0-4.el9_6.x86_64"
  ],
  "full_text": "[1.0.0-4]\n- Fix axis inversion on the first relative dial  (RHEL-106467)\n\n[1.0.0-3]\n- Map ABS_THROTTLE to ring2 on all dualring devices (RHEL-106467)\n\n[1.0.0-2]\n- Add support for Wacom Intuos Pro 3rd Gen (RHEL-106467)\n\nReferences:\nhttps://linux.oracle.com/errata/ELBA-2025-15892.html"
}