{
  "id": "ELBA-2025-20371-0",
  "vendor": "Oracle",
  "type": "Bug Fix Advisory (ELBA)",
  "kernel_type": "AppStream",
  "title": "lftp bug fix and enhancement update",
  "issuedDate": "2025-11-25T00:00:00Z",
  "updatedDate": "2025-11-25T00:00:00Z",
  "pubDate": "2025-11-25T00:00:00Z",
  "dateStr": "2025-11-25",
  "url": "https://linux.oracle.com/errata/ELBA-2025-20371-0.html",
  "severity": "None",
  "overview": "An update for Oracle Linux is now available for Oracle Linux 10.",
  "description": "[4.9.2-19]\n- Do not wait for server close-notify on TLS close\n- Resolves: RHEL-100407\n\n[4.9.2-18]\n- Improve fix for RHEL-91005\n- Resolves: RHEL-91005\n\n[4.9.2-17]\n- Ensure proper closing of TLS connection\n- Resolves: RHEL-91005",
  "affected_products": [
    "Oracle Linux 10 for x86_64",
    "Oracle Linux 10 for aarch64"
  ],
  "cves": [],
  "packages": [
    "lftp-4.9.2-19.el10.src",
    "lftp-4.9.2-19.el10.x86_64"
  ],
  "full_text": "[4.9.2-19]\n- Do not wait for server close-notify on TLS close\n- Resolves: RHEL-100407\n\n[4.9.2-18]\n- Improve fix for RHEL-91005\n- Resolves: RHEL-91005\n\n[4.9.2-17]\n- Ensure proper closing of TLS connection\n- Resolves: RHEL-91005\n\nReferences:\nhttps://linux.oracle.com/errata/ELBA-2025-20371-0.html"
}