{
  "id": "ELBA-2026-0439",
  "url": "https://oss.oracle.com/pipermail/el-errata/2026-January/019492.html",
  "synopsis": "[El-errata] ELBA-2026-0439 Oracle Linux 10 openssl bug fix and enhancement update",
  "dateStr": "2026-January",
  "type": "Mailing List Announcement",
  "severity": "",
  "overview": "Oracle Linux Bug Fix Advisory ELBA-2026-0439",
  "description": "[3.5.1-5.0.1]\n- Replace upstream references [Orabug: 34340177]\n- Update FIPS provider name [Orabug: 35824276]\n\n[1:3.5.1-5]\n- Do not make key share choice in tls1_set_groups()\n  Resolves: RHEL-130992",
  "affected_products": [
    "Oracle Linux 10"
  ],
  "packages": [
    "openssl-3.5.1-5.0.1.el10_1.x86_64.rpm",
    "openssl-devel-3.5.1-5.0.1.el10_1.x86_64.rpm",
    "openssl-libs-3.5.1-5.0.1.el10_1.x86_64.rpm",
    "openssl-perl-3.5.1-5.0.1.el10_1.x86_64.rpm",
    "openssl-3.5.1-5.0.1.el10_1.aarch64.rpm",
    "openssl-devel-3.5.1-5.0.1.el10_1.aarch64.rpm",
    "openssl-libs-3.5.1-5.0.1.el10_1.aarch64.rpm",
    "openssl-perl-3.5.1-5.0.1.el10_1.aarch64.rpm"
  ],
  "cves": [],
  "fixes": "",
  "notes": "",
  "full_text": "Oracle Linux Bug Fix Advisory ELBA-2026-0439\n\nhttp://linux.oracle.com/errata/ELBA-2026-0439.html\n\nThe following updated rpms for Oracle Linux 10 have been uploaded to the Unbreakable Linux Network:\n\nx86_64:\nopenssl-3.5.1-5.0.1.el10_1.x86_64.rpm\nopenssl-devel-3.5.1-5.0.1.el10_1.x86_64.rpm\nopenssl-libs-3.5.1-5.0.1.el10_1.x86_64.rpm\nopenssl-perl-3.5.1-5.0.1.el10_1.x86_64.rpm\n\naarch64:\nopenssl-3.5.1-5.0.1.el10_1.aarch64.rpm\nopenssl-devel-3.5.1-5.0.1.el10_1.aarch64.rpm\nopenssl-libs-3.5.1-5.0.1.el10_1.aarch64.rpm\nopenssl-perl-3.5.1-5.0.1.el10_1.aarch64.rpm\n\n\nSRPMS:\nhttp://oss.oracle.com/ol10/SRPMS-updates/openssl-3.5.1-5.0.1.el10_1.src.rpm\n\n\n\nDescription of changes:\n\n[3.5.1-5.0.1]\n- Replace upstream references [Orabug: 34340177]\n- Update FIPS provider name [Orabug: 35824276]\n\n[1:3.5.1-5]\n- Do not make key share choice in tls1_set_groups()\n  Resolves: RHEL-130992",
  "vendor": "Oracle"
}