{
  "id": "USN-7758-4",
  "vendor": "Canonical / Ubuntu",
  "type": "Ubuntu Security Notice (USN)",
  "title": "linux-oracle-6.8 vulnerability",
  "issuedDate": "2025-09-19T10:20:30Z",
  "updatedDate": "2026-02-10T04:49:49Z",
  "pubDate": "2025-09-19T10:20:30Z",
  "dateStr": "2025-09-19",
  "url": "https://ubuntu.com/security/notices/USN-7758-4",
  "severity": "None",
  "overview": "linux-oracle-6.8 vulnerability",
  "description": "It was discovered that the AF_UNIX socket garbage collection implementation\nin Ubuntu Noble's 6.8 kernel did not properly handle out-of-band (OOB)\nmessages, leading to a use-after-free vulnerability. An attacker could use\nthis to cause a denial of service (system crash) or possibly execute\narbitrary code.\n",
  "affected_products": [
    "Ubuntu 22.04 LTS"
  ],
  "cves": [],
  "packages": [
    "linux-buildinfo-6.8.0-1035-oracle-6.8.0-1035.36~22.04.1",
    "linux-buildinfo-6.8.0-1035-oracle-64k-6.8.0-1035.36~22.04.1",
    "linux-headers-6.8.0-1035-oracle-6.8.0-1035.36~22.04.1",
    "linux-headers-6.8.0-1035-oracle-64k-6.8.0-1035.36~22.04.1",
    "linux-image-unsigned-6.8.0-1035-oracle-6.8.0-1035.36~22.04.1",
    "linux-image-unsigned-6.8.0-1035-oracle-64k-6.8.0-1035.36~22.04.1",
    "linux-modules-6.8.0-1035-oracle-6.8.0-1035.36~22.04.1",
    "linux-modules-6.8.0-1035-oracle-64k-6.8.0-1035.36~22.04.1",
    "linux-modules-extra-6.8.0-1035-oracle-6.8.0-1035.36~22.04.1",
    "linux-modules-extra-6.8.0-1035-oracle-64k-6.8.0-1035.36~22.04.1",
    "linux-oracle-6.8-headers-6.8.0-1035-6.8.0-1035.36~22.04.1",
    "linux-oracle-6.8-tools-6.8.0-1035-6.8.0-1035.36~22.04.1",
    "linux-tools-6.8.0-1035-oracle-6.8.0-1035.36~22.04.1",
    "linux-tools-6.8.0-1035-oracle-64k-6.8.0-1035.36~22.04.1"
  ],
  "full_text": "It was discovered that the AF_UNIX socket garbage collection implementation\nin Ubuntu Noble's 6.8 kernel did not properly handle out-of-band (OOB)\nmessages, leading to a use-after-free vulnerability. An attacker could use\nthis to cause a denial of service (system crash) or possibly execute\narbitrary code.\n"
}
