{
  "id": "RHBA-2025:20266",
  "vendor": "Red Hat",
  "type": "Bug Fix Advisory (RHBA)",
  "title": "Red Hat Bug Fix Advisory: xdg-user-dirs bug fix and enhancement update",
  "issuedDate": "2025-11-11T07:25:53Z",
  "updatedDate": "2025-11-11T07:25:53Z",
  "pubDate": "2025-11-11T07:25:53Z",
  "dateStr": "2025-11-11",
  "url": "https://access.redhat.com/errata/RHBA-2025:20266",
  "severity": "None",
  "overview": "An update for xdg-user-dirs is now available for Red Hat Enterprise Linux 10.",
  "description": "For detailed information on changes in this release, see the Red Hat Enterprise Linux 10.1 Release Notes linked from the References section.",
  "affected_products": [
    "Red Hat Enterprise Linux for x86_64 10 x86_64",
    "Red Hat Enterprise Linux for Power, little endian",
    "Red Hat Enterprise Linux for IBM z Systems",
    "Red Hat Enterprise Linux for ARM 64"
  ],
  "cves": [],
  "packages": [
    "xdg-user-dirs-0.18-7.el10.src",
    "xdg-user-dirs-0.18-7.el10.x86_64",
    "xdg-user-dirs-debuginfo-0.18-7.el10.x86_64",
    "xdg-user-dirs-debugsource-0.18-7.el10.x86_64",
    "xdg-user-dirs-0.18-7.el10.s390x",
    "xdg-user-dirs-debuginfo-0.18-7.el10.s390x",
    "xdg-user-dirs-debugsource-0.18-7.el10.s390x",
    "xdg-user-dirs-0.18-7.el10.ppc64le",
    "xdg-user-dirs-debuginfo-0.18-7.el10.ppc64le",
    "xdg-user-dirs-debugsource-0.18-7.el10.ppc64le",
    "xdg-user-dirs-0.18-7.el10.aarch64",
    "xdg-user-dirs-debuginfo-0.18-7.el10.aarch64",
    "xdg-user-dirs-debugsource-0.18-7.el10.aarch64"
  ],
  "fixes": [
    {
      "id": "RHEL-79119",
      "url": "https://issues.redhat.com/browse/RHEL-79119",
      "description": "xdg-user-dirs sometimes does not populate properly"
    }
  ],
  "full_text": "An update for xdg-user-dirs is now available for Red Hat Enterprise Linux 10.\n\nFor detailed information on changes in this release, see the Red Hat Enterprise Linux 10.1 Release Notes linked from the References section."
}