{
  "id": "RHBA-2025:23337",
  "vendor": "Red Hat",
  "type": "Bug Fix Advisory (RHBA)",
  "title": "Red Hat Bug Fix Advisory: man-pages bug fix and enhancement update",
  "issuedDate": "2025-12-18T10:48:16Z",
  "updatedDate": "2025-12-18T10:48:16Z",
  "pubDate": "2025-12-18T10:48:16Z",
  "dateStr": "2025-12-18",
  "url": "https://access.redhat.com/errata/RHBA-2025:23337",
  "severity": "None",
  "overview": "An update for man-pages is now available for Red Hat Enterprise Linux 10.",
  "description": "The man-pages package provides man (manual) pages from the Linux Documentation Project (LDP).Bug Fix(es) and Enhancement(s): man-pages: Add update for RWF_ATOMIC [rhel-9] (JIRA:RHEL-87625)  man-pages: Errata work on RHEL-9.7.0.Z (2025:155133) (JIRA:RHEL-120486)  man-page: madvise(2) can return -EBUSY on MADV_SOFT_OFFLINE requests [rhel-9.7.z] (JIRA:RHEL-34105)",
  "affected_products": [
    "Red Hat Enterprise Linux for Power, little endian",
    "Red Hat Enterprise Linux for ARM 64",
    "Red Hat Enterprise Linux for IBM z Systems",
    "Red Hat Enterprise Linux for x86_64 10 x86_64"
  ],
  "cves": [],
  "packages": [
    "man-pages-6.04-9.el9_7.src",
    "man-pages-6.04-9.el9_7.noarch"
  ],
  "fixes": [
    {
      "id": "RHEL-87625",
      "url": "https://issues.redhat.com/browse/RHEL-87625",
      "description": "man-pages: Add update for RWF_ATOMIC [rhel-9]"
    },
    {
      "id": "RHEL-34105",
      "url": "https://issues.redhat.com/browse/RHEL-34105",
      "description": "man-page: madvise(2) can return -EBUSY on MADV_SOFT_OFFLINE requests [rhel-9.7.z]"
    }
  ],
  "full_text": "An update for man-pages is now available for Red Hat Enterprise Linux 10.\n\nThe man-pages package provides man (manual) pages from the Linux Documentation Project (LDP).Bug Fix(es) and Enhancement(s): man-pages: Add update for RWF_ATOMIC [rhel-9] (JIRA:RHEL-87625)  man-pages: Errata work on RHEL-9.7.0.Z (2025:155133) (JIRA:RHEL-120486)  man-page: madvise(2) can return -EBUSY on MADV_SOFT_OFFLINE requests [rhel-9.7.z] (JIRA:RHEL-34105)"
}