{
  "id": "RHBA-2025:23293",
  "vendor": "Red Hat",
  "type": "Bug Fix Advisory (RHBA)",
  "title": "Red Hat Bug Fix Advisory: nodejs24 bug fix and enhancement update",
  "issuedDate": "2025-12-18T09:19:12Z",
  "updatedDate": "2025-12-18T09:19:12Z",
  "pubDate": "2025-12-18T09:19:12Z",
  "dateStr": "2025-12-18",
  "url": "https://access.redhat.com/errata/RHBA-2025:23293",
  "severity": "None",
  "overview": "An update for nodejs24 is now available for Red Hat Enterprise Linux 10.",
  "description": "Node.js is a platform built on Chrome's JavaScript runtime for easily building fast, scalable network applications. Node.js uses an event-driven, non-blocking I/O model that makes it lightweight and efficient, perfect for data-intensive real-time applications that run across distributed devices.Bug Fix(es) and Enhancement(s): nodejs24: Rebase to the latest Node.js 24 release [rhel-10.1.z] (JIRA:RHEL-129209)",
  "affected_products": [
    "Red Hat Enterprise Linux for ARM 64",
    "Red Hat Enterprise Linux for IBM z Systems",
    "Red Hat Enterprise Linux for x86_64 10 x86_64",
    "Red Hat Enterprise Linux for Power, little endian"
  ],
  "cves": [],
  "packages": [
    "nodejs24-24.11.1-1.el10_1.src",
    "nodejs24-24.11.1-1.el10_1.x86_64",
    "nodejs24-debuginfo-24.11.1-1.el10_1.x86_64",
    "nodejs24-debugsource-24.11.1-1.el10_1.x86_64",
    "nodejs24-devel-24.11.1-1.el10_1.x86_64",
    "nodejs24-docs-24.11.1-1.el10_1.noarch",
    "nodejs24-full-i18n-24.11.1-1.el10_1.x86_64",
    "nodejs24-libs-24.11.1-1.el10_1.x86_64",
    "nodejs24-libs-debuginfo-24.11.1-1.el10_1.x86_64",
    "nodejs24-npm-11.6.2-1.24.11.1.1.el10_1.noarch",
    "nodejs24-24.11.1-1.el10_1.s390x",
    "nodejs24-debuginfo-24.11.1-1.el10_1.s390x",
    "nodejs24-debugsource-24.11.1-1.el10_1.s390x",
    "nodejs24-devel-24.11.1-1.el10_1.s390x",
    "nodejs24-full-i18n-24.11.1-1.el10_1.s390x",
    "nodejs24-libs-24.11.1-1.el10_1.s390x",
    "nodejs24-libs-debuginfo-24.11.1-1.el10_1.s390x",
    "nodejs24-24.11.1-1.el10_1.ppc64le",
    "nodejs24-debuginfo-24.11.1-1.el10_1.ppc64le",
    "nodejs24-debugsource-24.11.1-1.el10_1.ppc64le",
    "nodejs24-devel-24.11.1-1.el10_1.ppc64le",
    "nodejs24-full-i18n-24.11.1-1.el10_1.ppc64le",
    "nodejs24-libs-24.11.1-1.el10_1.ppc64le",
    "nodejs24-libs-debuginfo-24.11.1-1.el10_1.ppc64le",
    "nodejs24-24.11.1-1.el10_1.aarch64",
    "nodejs24-debuginfo-24.11.1-1.el10_1.aarch64",
    "nodejs24-debugsource-24.11.1-1.el10_1.aarch64",
    "nodejs24-devel-24.11.1-1.el10_1.aarch64",
    "nodejs24-full-i18n-24.11.1-1.el10_1.aarch64",
    "nodejs24-libs-24.11.1-1.el10_1.aarch64",
    "nodejs24-libs-debuginfo-24.11.1-1.el10_1.aarch64"
  ],
  "fixes": [],
  "full_text": "An update for nodejs24 is now available for Red Hat Enterprise Linux 10.\n\nNode.js is a platform built on Chrome's JavaScript runtime for easily building fast, scalable network applications. Node.js uses an event-driven, non-blocking I/O model that makes it lightweight and efficient, perfect for data-intensive real-time applications that run across distributed devices.Bug Fix(es) and Enhancement(s): nodejs24: Rebase to the latest Node.js 24 release [rhel-10.1.z] (JIRA:RHEL-129209)"
}