{
  "id": "RHBA-2025:20129",
  "vendor": "Red Hat",
  "type": "Bug Fix Advisory (RHBA)",
  "title": "Red Hat Bug Fix Advisory: libtracecmd bug fix and enhancement update",
  "issuedDate": "2025-11-11T07:25:11Z",
  "updatedDate": "2025-11-11T07:25:11Z",
  "pubDate": "2025-11-11T07:25:11Z",
  "dateStr": "2025-11-11",
  "url": "https://access.redhat.com/errata/RHBA-2025:20129",
  "severity": "None",
  "overview": "An update for libtracecmd is now available for Red Hat Enterprise Linux 10.",
  "description": "For detailed information on changes in this release, see the Red Hat Enterprise Linux 10 Release Notes linked from the References section.",
  "affected_products": [
    "Red Hat Enterprise Linux for Power, little endian",
    "Red Hat Enterprise Linux for ARM 64",
    "Red Hat Enterprise Linux for IBM z Systems",
    "Red Hat Enterprise Linux for x86_64 10 x86_64"
  ],
  "cves": [],
  "packages": [
    "libtracecmd-1.5.2-2.el10.src",
    "libtracecmd-1.5.2-2.el10.x86_64",
    "libtracecmd-debuginfo-1.5.2-2.el10.x86_64",
    "libtracecmd-debugsource-1.5.2-2.el10.x86_64",
    "libtracecmd-devel-1.5.2-2.el10.x86_64",
    "libtracecmd-1.5.2-2.el10.s390x",
    "libtracecmd-debuginfo-1.5.2-2.el10.s390x",
    "libtracecmd-debugsource-1.5.2-2.el10.s390x",
    "libtracecmd-devel-1.5.2-2.el10.s390x",
    "libtracecmd-1.5.2-2.el10.ppc64le",
    "libtracecmd-debuginfo-1.5.2-2.el10.ppc64le",
    "libtracecmd-debugsource-1.5.2-2.el10.ppc64le",
    "libtracecmd-devel-1.5.2-2.el10.ppc64le",
    "libtracecmd-1.5.2-2.el10.aarch64",
    "libtracecmd-debuginfo-1.5.2-2.el10.aarch64",
    "libtracecmd-debugsource-1.5.2-2.el10.aarch64",
    "libtracecmd-devel-1.5.2-2.el10.aarch64"
  ],
  "fixes": [
    {
      "id": "RHEL-80321",
      "url": "https://issues.redhat.com/browse/RHEL-80321",
      "description": "Failed to generate trace.dat for guest with error 'reading client -110 (Unknown error -110)'"
    }
  ],
  "full_text": "An update for libtracecmd is now available for Red Hat Enterprise Linux 10.\n\nFor detailed information on changes in this release, see the Red Hat Enterprise Linux 10 Release Notes linked from the References section."
}