{
  "id": "RHBA-2025:21019",
  "vendor": "Red Hat",
  "type": "Bug Fix Advisory (RHBA)",
  "title": "Red Hat Bug Fix Advisory: realmd bug fix and enhancement update",
  "issuedDate": "2025-11-11T18:27:49Z",
  "updatedDate": "2025-11-11T18:27:49Z",
  "pubDate": "2025-11-11T18:27:49Z",
  "dateStr": "2025-11-11",
  "url": "https://access.redhat.com/errata/RHBA-2025:21019",
  "severity": "None",
  "overview": "An update for realmd is now available for Red Hat Enterprise Linux 10.",
  "description": "The realmd DBus system service manages discovery of and enrollment in realms and domains, such as Active Directory or Identity Management (IdM).  The realmd service detects available domains, automatically configures the system, and joins it as an account to a domain.Bug Fix(es) and Enhancement(s): Add renew command (JIRA:RHEL-117645)",
  "affected_products": [
    "Red Hat Enterprise Linux for IBM z Systems",
    "Red Hat Enterprise Linux for ARM 64",
    "Red Hat Enterprise Linux for Power, little endian",
    "Red Hat Enterprise Linux for x86_64 10 x86_64"
  ],
  "cves": [],
  "packages": [
    "realmd-0.17.1-13.el10_1.src",
    "realmd-0.17.1-13.el10_1.x86_64",
    "realmd-debuginfo-0.17.1-13.el10_1.x86_64",
    "realmd-debugsource-0.17.1-13.el10_1.x86_64",
    "realmd-0.17.1-13.el10_1.s390x",
    "realmd-debuginfo-0.17.1-13.el10_1.s390x",
    "realmd-debugsource-0.17.1-13.el10_1.s390x",
    "realmd-0.17.1-13.el10_1.ppc64le",
    "realmd-debuginfo-0.17.1-13.el10_1.ppc64le",
    "realmd-debugsource-0.17.1-13.el10_1.ppc64le",
    "realmd-0.17.1-13.el10_1.aarch64",
    "realmd-debuginfo-0.17.1-13.el10_1.aarch64",
    "realmd-debugsource-0.17.1-13.el10_1.aarch64"
  ],
  "fixes": [
    {
      "id": "RHEL-117645",
      "url": "https://issues.redhat.com/browse/RHEL-117645",
      "description": "Add renew command"
    }
  ],
  "full_text": "An update for realmd is now available for Red Hat Enterprise Linux 10.\n\nThe realmd DBus system service manages discovery of and enrollment in realms and domains, such as Active Directory or Identity Management (IdM).  The realmd service detects available domains, automatically configures the system, and joins it as an account to a domain.Bug Fix(es) and Enhancement(s): Add renew command (JIRA:RHEL-117645)"
}