{
  "id": "RHBA-2025:20951",
  "vendor": "Red Hat",
  "type": "Bug Fix Advisory (RHBA)",
  "title": "Red Hat Bug Fix Advisory: gdm, gnome-shell, and gsettings-desktop-schemas bug fix and enhancement update",
  "issuedDate": "2025-11-11T11:47:34Z",
  "updatedDate": "2025-11-11T11:47:34Z",
  "pubDate": "2025-11-11T11:47:34Z",
  "dateStr": "2025-11-11",
  "url": "https://access.redhat.com/errata/RHBA-2025:20951",
  "severity": "None",
  "overview": "An update for gdm, is now available for Red Hat Enterprise Linux 10.",
  "description": "The GNOME Display Manager (GDM) provides the graphical login screen. The screen is shown shortly after boot, after log out, and when switching the current user.Bug Fix(es) and Enhancement(s): Gnome option to disable showing password on login/locl screen \"disable-show-password\" missing in RHEL9 [rhel-9.7.z] (JIRA:RHEL-123139)  Gnome option to disable showing password on login/locl screen \"disable-show-password\" missing in RHEL9 [rhel-9.7.z] (JIRA:RHEL-123140)  Regression in AllowMultipleSessionsPerUser  (JIRA:RHEL-109190)  Regression in AllowMultipleSessionsPerUser  (JIRA:RHEL-123357)",
  "affected_products": [
    "Red Hat CodeReady Linux Builder for Power, little endian",
    "Red Hat CodeReady Linux Builder for ARM 64",
    "Red Hat Enterprise Linux for x86_64 10 x86_64",
    "Red Hat CodeReady Linux Builder for x86_64 10 x86_64",
    "Red Hat Enterprise Linux for IBM z Systems",
    "Red Hat CodeReady Linux Builder for IBM z Systems",
    "Red Hat Enterprise Linux for ARM 64",
    "Red Hat Enterprise Linux for Power, little endian"
  ],
  "cves": [],
  "packages": [
    "gdm-40.1-38.el9_7.src",
    "gnome-shell-40.10-31.el9_7.src",
    "gsettings-desktop-schemas-40.0-8.el9_7.src",
    "gdm-40.1-38.el9_7.i686",
    "gdm-40.1-38.el9_7.x86_64",
    "gdm-debuginfo-40.1-38.el9_7.i686",
    "gdm-debuginfo-40.1-38.el9_7.x86_64",
    "gdm-debugsource-40.1-38.el9_7.i686",
    "gdm-debugsource-40.1-38.el9_7.x86_64",
    "gnome-shell-40.10-31.el9_7.x86_64",
    "gnome-shell-debuginfo-40.10-31.el9_7.x86_64",
    "gnome-shell-debugsource-40.10-31.el9_7.x86_64",
    "gsettings-desktop-schemas-40.0-8.el9_7.i686",
    "gsettings-desktop-schemas-40.0-8.el9_7.x86_64",
    "gsettings-desktop-schemas-devel-40.0-8.el9_7.i686",
    "gsettings-desktop-schemas-devel-40.0-8.el9_7.x86_64",
    "gdm-40.1-38.el9_7.s390x",
    "gdm-debuginfo-40.1-38.el9_7.s390x",
    "gdm-debugsource-40.1-38.el9_7.s390x",
    "gnome-shell-40.10-31.el9_7.s390x",
    "gnome-shell-debuginfo-40.10-31.el9_7.s390x",
    "gnome-shell-debugsource-40.10-31.el9_7.s390x",
    "gsettings-desktop-schemas-40.0-8.el9_7.s390x",
    "gsettings-desktop-schemas-devel-40.0-8.el9_7.s390x",
    "gdm-40.1-38.el9_7.ppc64le",
    "gdm-debuginfo-40.1-38.el9_7.ppc64le",
    "gdm-debugsource-40.1-38.el9_7.ppc64le",
    "gnome-shell-40.10-31.el9_7.ppc64le",
    "gnome-shell-debuginfo-40.10-31.el9_7.ppc64le",
    "gnome-shell-debugsource-40.10-31.el9_7.ppc64le",
    "gsettings-desktop-schemas-40.0-8.el9_7.ppc64le",
    "gsettings-desktop-schemas-devel-40.0-8.el9_7.ppc64le",
    "gdm-40.1-38.el9_7.aarch64",
    "gdm-debuginfo-40.1-38.el9_7.aarch64",
    "gdm-debugsource-40.1-38.el9_7.aarch64",
    "gnome-shell-40.10-31.el9_7.aarch64",
    "gnome-shell-debuginfo-40.10-31.el9_7.aarch64",
    "gnome-shell-debugsource-40.10-31.el9_7.aarch64",
    "gsettings-desktop-schemas-40.0-8.el9_7.aarch64",
    "gsettings-desktop-schemas-devel-40.0-8.el9_7.aarch64",
    "gdm-devel-40.1-38.el9_7.i686",
    "gdm-devel-40.1-38.el9_7.x86_64",
    "gdm-pam-extensions-devel-40.1-38.el9_7.i686",
    "gdm-pam-extensions-devel-40.1-38.el9_7.x86_64",
    "gdm-devel-40.1-38.el9_7.ppc64le",
    "gdm-pam-extensions-devel-40.1-38.el9_7.ppc64le",
    "gdm-devel-40.1-38.el9_7.aarch64",
    "gdm-pam-extensions-devel-40.1-38.el9_7.aarch64",
    "gdm-devel-40.1-38.el9_7.s390x",
    "gdm-pam-extensions-devel-40.1-38.el9_7.s390x"
  ],
  "fixes": [],
  "full_text": "An update for gdm, is now available for Red Hat Enterprise Linux 10.\n\nThe GNOME Display Manager (GDM) provides the graphical login screen. The screen is shown shortly after boot, after log out, and when switching the current user.Bug Fix(es) and Enhancement(s): Gnome option to disable showing password on login/locl screen \"disable-show-password\" missing in RHEL9 [rhel-9.7.z] (JIRA:RHEL-123139)  Gnome option to disable showing password on login/locl screen \"disable-show-password\" missing in RHEL9 [rhel-9.7.z] (JIRA:RHEL-123140)  Regression in AllowMultipleSessionsPerUser  (JIRA:RHEL-109190)  Regression in AllowMultipleSessionsPerUser  (JIRA:RHEL-123357)"
}